rushcards/__init__.py
rushcards/__main__.py
rushcards/base.py
rushcards/cli.py
rushcards/draw.py
rushcards/puzzle.py
rushcards/puzzles.pickle
rushcards/tools/__init__.py
rushcards/tools/mkpuzzles.py
rushcards/tools/statistics.py
rushcards-0.2.0.dist-info/METADATA
rushcards-0.2.0.dist-info/WHEEL
rushcards-0.2.0.dist-info/entry_points.txt
rushcards-0.2.0.dist-info/licenses/LICENSE.md
rushcards-0.2.0.dist-info/RECORD
