Metadata-Version: 2.3
Name: rushcards
Version: 0.2.0
Summary: A Python command line application for generating Rush Hour puzzle cards.
Project-URL: Homepage, https://github.com/marfire/rushcards
Project-URL: Issues, https://github.com/marfire/rushcards/issues
Author-email: Kevin Christopher Henry <k@severian.com>
License-Expression: MIT
License-File: LICENSE.md
Keywords: games,rush,rush-hour
Classifier: Development Status :: 4 - Beta
Classifier: License :: OSI Approved :: MIT License
Classifier: Operating System :: OS Independent
Classifier: Programming Language :: Python :: 3
Classifier: Programming Language :: Python :: 3.6
Classifier: Programming Language :: Python :: 3.7
Classifier: Programming Language :: Python :: 3.8
Classifier: Programming Language :: Python :: 3.9
Classifier: Programming Language :: Python :: 3.10
Classifier: Programming Language :: Python :: 3.11
Classifier: Programming Language :: Python :: 3.12
Classifier: Programming Language :: Python :: 3.13
Classifier: Topic :: Games/Entertainment :: Board Games
Classifier: Topic :: Games/Entertainment :: Puzzle Games
Requires-Python: >=3.6
Requires-Dist: pillow>=9.0.1
